ccg/Carray.py
ccg/Cnamespace.py
ccg/Cusing.py
ccg/Cvariable.py
ccg/__init__.py
ccg/doc.py
ccg/style.py
ccg/expressions/Ccast.py
ccg/expressions/Cexpression.py
ccg/expressions/Cliteral.py
ccg/expressions/Coperators.py
ccg/expressions/__init__.py
ccg/statements/Citeration.py
ccg/statements/Cjump.py
ccg/statements/Cselection.py
ccg/statements/Cstatement.py
ccg/statements/__init__.py
ccg/types/Cclass.py
ccg/types/Cfunction.py
ccg/types/CstdTypes.py
ccg/types/Cstruct.py
ccg/types/Ctypes.py
ccg/types/Cunion.py
ccg/types/__init__.py
ccg-0.1.0.dist-info/LICENSE
ccg-0.1.0.dist-info/METADATA
ccg-0.1.0.dist-info/WHEEL
ccg-0.1.0.dist-info/top_level.txt
ccg-0.1.0.dist-info/RECORD
