Metadata-Version: 2.1
Name: ccg
Version: 0.1.0
Summary: C/C++ code generation framework
Home-page: https://github.com/polfeliu/CCG
Author: Pol Feliu Cuberes
Author-email: feliupol@gmail.com
License: Attribution-NoDerivatives 4.0 International (CC BY-ND 4.0)
Keywords: ccg c cpp codegen generation
Platform: UNKNOWN
License-File: LICENSE
